auro_sensors/__init__.py
auro_sensors/cameras/__init__.py
auro_sensors/cameras/basic_camera.py
auro_sensors/cameras/realsense_camera.py
auro_sensors/cameras/realsense_camera_ros1.py
auro_sensors/utils/__init__.py
auro_sensors/utils/aruco.py
auro_sensors-0.0.2.dist-info/METADATA
auro_sensors-0.0.2.dist-info/WHEEL
auro_sensors-0.0.2.dist-info/top_level.txt
auro_sensors-0.0.2.dist-info/RECORD
