Metadata-Version: 2.1
Name: auro_sensors
Version: 0.0.2
Summary: sensors for auromix application
Home-page: https://github.com/Auromix/auro_sensors
Author: Herman Ye
Author-email: hermanye233@icloud.com
Keywords: auro_sensors
Classifier: Development Status :: 2 - Pre-Alpha
Classifier: Intended Audience :: Developers
Classifier: Natural Language :: English
Classifier: Programming Language :: Python :: 3
Classifier: Programming Language :: Python :: 3.8
Requires-Python: >=3.8
Requires-Dist: auro-utils
Requires-Dist: pyrealsense2 >=2.54
Requires-Dist: matplotlib >=3.7
Requires-Dist: imageio >=2.34
Requires-Dist: transforms3d >=0.4
Requires-Dist: opencv-contrib-python >=4.9
Requires-Dist: opencv-python >=4.9
